rust_helper-0.1.0.dist-info/METADATA
rust_helper-0.1.0.dist-info/WHEEL
rust_helper-0.1.0.dist-info/licenses/LICENSE
rust_helper.libs/libgcc_s-e52197c3.so.1
rust_helper/__init__.py
rust_helper/rust_helper.cpython-313-aarch64-linux-musl.so
rust_helper-0.1.0.dist-info/RECORD
